deephaven_example_app/__init__.py
deephaven_example_app/__main__.py
deephaven_example_app/coinbase.py
deephaven_example_app-0.3.0.dist-info/METADATA
deephaven_example_app-0.3.0.dist-info/WHEEL
deephaven_example_app-0.3.0.dist-info/top_level.txt
deephaven_example_app-0.3.0.dist-info/RECORD
