Metadata-Version: 2.1
Name: deephaven-example-app
Version: 0.3.0
Summary: Deephaven Example Application
Home-page: https://github.com/deephaven-examples/deephaven-server-pypi-app
Author: Devin Smith
Author-email: devinsmith@deephaven.io
Project-URL: Source Code, https://github.com/deephaven-examples/deephaven-server-pypi-app
Project-URL: Bug Tracker, https://github.com/deephaven-examples/deephaven-server-pypi-app/issues
Keywords: deephaven,streaming,websockets,coinbase
Platform: any
Classifier: Programming Language :: Python :: 3
Classifier: License :: OSI Approved :: Apache Software License
Classifier: Operating System :: OS Independent
Classifier: Development Status :: 3 - Alpha
Requires-Dist: deephaven-server (>=0.17.0)
Requires-Dist: websocket-client
